advanced_password_validator/__init__.py
advanced_password_validator/mode.py
advanced_password_validator/rules.py
advanced_password_validator/validator.py
advanced_password_validator/data/__init__.py
advanced_password_validator/data/blacklist.txt
advanced_password_validator/data/common_passwords.txt
advanced_password_validator-1.0.1.dist-info/licenses/LICENSE
advanced_password_validator-1.0.1.dist-info/METADATA
advanced_password_validator-1.0.1.dist-info/WHEEL
advanced_password_validator-1.0.1.dist-info/top_level.txt
advanced_password_validator-1.0.1.dist-info/RECORD
