Metadata-Version: 2.4
Name: advanced_password_validator
Version: 1.0.1
Summary: A dynamic password validation system with preconfigured modes and rule-based design
Author-email: HysingerDev <HysingerDev@gmail.com>
License: MIT LICENSE
Project-URL: homepage, https://github.com/MassivelyOverthinking/Password_validator
Project-URL: source, https://github.com/MassivelyOverthinking/Password_validator
Project-URL: bugTracker, https://github.com/MassivelyOverthinking/Password_validator/issues
Project-URL: documentation, https://github.com/MassivelyOverthinking/Password_validator#readme
Keywords: password,validation,security,rules,authentication,python
Classifier: Programming Language :: Python :: 3
Classifier: License :: OSI Approved :: MIT License
Classifier: Operating System :: OS Independent
Classifier: Topic :: Security :: Cryptography
Classifier: Topic :: Software Development :: Libraries :: Python Modules
Classifier: Intended Audience :: Developers
Requires-Python: >=3.8
License-File: LICENSE
Dynamic: license-file
